{"version":2,"kind":"Notebook","sha256":"5dc4a26f5952bb79ea07bad81ba46405d04a3e7a86e5c38108550dc31ae38ec9","slug":"notebooks.example-workflows.tracer-example","location":"/notebooks/example-workflows/tracer-example.ipynb","dependencies":[],"frontmatter":{"title":"Plotting Data from a Field Campaign (TRACER)","content_includes_title":true,"kernelspec":{"name":"python3","display_name":"Python 3","language":"python"},"authors":[{"nameParsed":{"literal":"Max Grover","given":"Max","family":"Grover"},"name":"Max Grover","id":"contributors-myst-generated-uid-0"},{"nameParsed":{"literal":"Zachary Sherman","given":"Zachary","family":"Sherman"},"name":"Zachary Sherman","id":"contributors-myst-generated-uid-1"},{"nameParsed":{"literal":"Milind Sharma","given":"Milind","family":"Sharma"},"name":"Milind Sharma","id":"contributors-myst-generated-uid-2"}],"open_access":true,"license":{"content":{"id":"CC-BY-4.0","url":"https://creativecommons.org/licenses/by/4.0/","name":"Creative Commons Attribution 4.0 International","free":true,"CC":true},"code":{"id":"Apache-2.0","url":"https://opensource.org/licenses/Apache-2.0","name":"Apache License 2.0","free":true,"osi":true}},"github":"https://github.com/projectpythia/radar-cookbook","copyright":"2024","affiliations":[{"id":"UAlbany","name":"University at Albany (SUNY)","department":"Atmospheric and Environmental Sciences","url":"https://www.albany.edu/daes"},{"id":"CISL","name":"NSF National Center for Atmospheric Research","department":"Computational and Information Systems Lab","url":"https://www.cisl.ucar.edu"},{"id":"Unidata","name":"NSF Unidata","url":"https://www.unidata.ucar.edu"},{"id":"Argonne","name":"Argonne National Laboratory","department":"Environmental Science Division","url":"https://www.anl.gov/evs"},{"id":"CarbonPlan","name":"CarbonPlan","url":"https://carbonplan.org"},{"id":"NVIDIA","name":"NVIDIA Corporation","url":"https://www.nvidia.com/"}],"abbreviations":{"ARM":"Atmospheric Radiation Measurement"},"numbering":{"title":{"offset":1}},"source_url":"https://github.com/projectpythia/radar-cookbook/blob/main/notebooks/example-workflows/tracer-example.ipynb","edit_url":"https://github.com/projectpythia/radar-cookbook/edit/main/notebooks/example-workflows/tracer-example.ipynb","thumbnail":"/radar-cookbook/build/storm-animation-90e9470d8c2e5a01e1aefb0d24151a42.gif","exports":[{"format":"ipynb","filename":"tracer-example.ipynb","url":"/radar-cookbook/build/tracer-example-339a2661f8a052e119f51f536120f05a.ipynb"}]},"widgets":{},"mdast":{"type":"root","children":[{"type":"block","kind":"notebook-content","children":[{"type":"paragraph","position":{"start":{"line":1,"column":1},"end":{"line":1,"column":1}},"children":[{"type":"image","url":"/radar-cookbook/build/storm-animation-90e9470d8c2e5a01e1aefb0d24151a42.gif","alt":"TRACER Animation","width":600,"key":"s8ZQafFCh5","urlSource":"../images/storm-animation.gif"}],"key":"qnIXhurQdS"},{"type":"heading","depth":1,"position":{"start":{"line":2,"column":1},"end":{"line":2,"column":1}},"children":[{"type":"text","value":"Plotting Data from a Field Campaign (TRACER)","position":{"start":{"line":2,"column":1},"end":{"line":2,"column":1}},"key":"PPNxAV5COj"}],"identifier":"plotting-data-from-a-field-campaign-tracer","label":"Plotting Data from a Field Campaign (TRACER)","html_id":"plotting-data-from-a-field-campaign-tracer","implicit":true,"key":"hYk0ilukzs"}],"key":"KNEqzx81H4"},{"type":"block","kind":"notebook-content","children":[{"type":"heading","depth":2,"position":{"start":{"line":1,"column":1},"end":{"line":1,"column":1}},"children":[{"type":"text","value":"Overview","position":{"start":{"line":1,"column":1},"end":{"line":1,"column":1}},"key":"iANJzNQhvG"}],"identifier":"overview","label":"Overview","html_id":"overview","implicit":true,"key":"DjLgbZvlLO"},{"type":"paragraph","position":{"start":{"line":3,"column":1},"end":{"line":3,"column":1}},"children":[{"type":"text","value":"Within this notebook, we will cover:","position":{"start":{"line":3,"column":1},"end":{"line":3,"column":1}},"key":"t20x0AU7Dc"}],"key":"cgCjD8iVsS"},{"type":"list","ordered":true,"start":1,"spread":false,"position":{"start":{"line":5,"column":1},"end":{"line":6,"column":1}},"children":[{"type":"listItem","spread":true,"position":{"start":{"line":5,"column":1},"end":{"line":5,"column":1}},"children":[{"type":"paragraph","children":[{"type":"text","value":"How to access data from the Atmospheric Radiation Measurment (","key":"rJnzX5YUe2"},{"type":"abbreviation","title":"Atmospheric Radiation Measurement","children":[{"type":"text","value":"ARM","key":"U1FHBdiS2e"}],"key":"LSkEXXLZcL"},{"type":"text","value":") user facility","key":"EyO4GniXV7"}],"key":"C6vam6M6nN"}],"key":"BSqiWbRYA5"},{"type":"listItem","spread":true,"position":{"start":{"line":6,"column":1},"end":{"line":6,"column":1}},"children":[{"type":"paragraph","children":[{"type":"text","value":"How to setup a workflow to plot both cross sections (RHIs) and horizontal scans (PPIs)","position":{"start":{"line":6,"column":1},"end":{"line":6,"column":1}},"key":"eT8wVkN9UU"}],"key":"IisGC0DJYD"}],"key":"vgFFtbhsVG"}],"key":"KWyp2EUJ9x"}],"key":"m0e66EWfiv"},{"type":"block","kind":"notebook-content","children":[{"type":"heading","depth":2,"position":{"start":{"line":1,"column":1},"end":{"line":1,"column":1}},"children":[{"type":"text","value":"Prerequisites","position":{"start":{"line":1,"column":1},"end":{"line":1,"column":1}},"key":"oxVQpR7ydp"}],"identifier":"prerequisites","label":"Prerequisites","html_id":"prerequisites","implicit":true,"key":"IGw4YIFKnL"},{"type":"table","position":{"start":{"line":2,"column":1},"end":{"line":5,"column":1}},"children":[{"type":"tableRow","position":{"start":{"line":2,"column":1},"end":{"line":2,"column":1}},"children":[{"type":"tableCell","header":true,"position":{"start":{"line":2,"column":1},"end":{"line":2,"column":1}},"children":[{"type":"text","value":"Concepts","position":{"start":{"line":2,"column":1},"end":{"line":2,"column":1}},"key":"tmpF561A2l"}],"key":"oydWnpsRHI"},{"type":"tableCell","header":true,"position":{"start":{"line":2,"column":1},"end":{"line":2,"column":1}},"children":[{"type":"text","value":"Importance","position":{"start":{"line":2,"column":1},"end":{"line":2,"column":1}},"key":"EczJoIdsZ1"}],"key":"OlKxI6hPvX"},{"type":"tableCell","header":true,"position":{"start":{"line":2,"column":1},"end":{"line":2,"column":1}},"children":[{"type":"text","value":"Notes","position":{"start":{"line":2,"column":1},"end":{"line":2,"column":1}},"key":"XzURIqeKcC"}],"key":"cQhXdPIUsq"}],"key":"TWpQbrh0te"},{"type":"tableRow","position":{"start":{"line":4,"column":1},"end":{"line":4,"column":1}},"children":[{"type":"tableCell","position":{"start":{"line":4,"column":1},"end":{"line":4,"column":1}},"children":[{"type":"link","url":"https://foundations.projectpythia.org/core/matplotlib/matplotlib-basics","position":{"start":{"line":4,"column":1},"end":{"line":4,"column":1}},"children":[{"type":"text","value":"Matplotlib Basics","position":{"start":{"line":4,"column":1},"end":{"line":4,"column":1}},"key":"gfU3tGe2zZ"}],"urlSource":"https://foundations.projectpythia.org/core/matplotlib/matplotlib-basics","key":"IlgPWRqtyI"}],"key":"rTG1HELtmy"},{"type":"tableCell","position":{"start":{"line":4,"column":1},"end":{"line":4,"column":1}},"children":[{"type":"text","value":"Required","position":{"start":{"line":4,"column":1},"end":{"line":4,"column":1}},"key":"grLcKIFldS"}],"key":"zaydx96UdV"},{"type":"tableCell","position":{"start":{"line":4,"column":1},"end":{"line":4,"column":1}},"children":[{"type":"text","value":"Basic plotting","position":{"start":{"line":4,"column":1},"end":{"line":4,"column":1}},"key":"anyXiTTGye"}],"key":"o5W063Px2h"}],"key":"AVs5El6PqS"},{"type":"tableRow","position":{"start":{"line":5,"column":1},"end":{"line":5,"column":1}},"children":[{"type":"tableCell","position":{"start":{"line":5,"column":1},"end":{"line":5,"column":1}},"children":[{"type":"link","url":"/notebooks/foundations/pyart-basics","position":{"start":{"line":5,"column":1},"end":{"line":5,"column":1}},"children":[{"type":"text","value":"Py-ART Basics","position":{"start":{"line":5,"column":1},"end":{"line":5,"column":1}},"key":"Ez6NU48jk4"}],"urlSource":"../foundations/pyart-basics","dataUrl":"/notebooks.foundations.pyart-basics.json","internal":true,"protocol":"file","key":"UdYRaEe19W"}],"key":"bMq8tdKiSu"},{"type":"tableCell","position":{"start":{"line":5,"column":1},"end":{"line":5,"column":1}},"children":[{"type":"text","value":"Required","position":{"start":{"line":5,"column":1},"end":{"line":5,"column":1}},"key":"nNrYi1efUa"}],"key":"mw28IP7cRt"},{"type":"tableCell","position":{"start":{"line":5,"column":1},"end":{"line":5,"column":1}},"children":[{"type":"text","value":"IO/Visualization","position":{"start":{"line":5,"column":1},"end":{"line":5,"column":1}},"key":"j9fmC653PA"}],"key":"p0lnuy7Rfn"}],"key":"Nd3NSvhFsn"}],"key":"WFDqSCrtJn"}],"key":"IuvAJVBdt7"},{"type":"block","kind":"notebook-content","children":[{"type":"thematicBreak","position":{"start":{"line":1,"column":1},"end":{"line":1,"column":1}},"key":"iSLywYquHc"},{"type":"heading","depth":2,"position":{"start":{"line":2,"column":1},"end":{"line":2,"column":1}},"children":[{"type":"text","value":"Imports","position":{"start":{"line":2,"column":1},"end":{"line":2,"column":1}},"key":"izfe6rEXo4"}],"identifier":"imports","label":"Imports","html_id":"imports","implicit":true,"key":"U6PFEAV97t"}],"key":"DUsYkCTpA6"},{"type":"block","kind":"notebook-code","children":[{"type":"code","lang":"python","executable":true,"value":"import glob\nimport os\nfrom pathlib import Path\n\nimport act\nimport imageio.v2 as imageio\nimport matplotlib\nimport matplotlib.pyplot as plt\nimport pyart","key":"Wb8DVhXx2D"},{"type":"output","id":"DAJZKgXiP29wNHXhUFtEN","data":[{"output_type":"stream","name":"stdout","text":"\n## You are using the Python ARM Radar Toolkit (Py-ART), an open source\n## library for working with weather radar data. Py-ART is partly\n## supported by the U.S. Department of Energy as part of the Atmospheric\n## Radiation Measurement (ARM) Climate Research Facility, an Office of\n## Science user facility.\n##\n## If you use this software to prepare a publication, please cite:\n##\n##     JJ Helmus and SM Collis, JORS 2016, doi: 10.5334/jors.119\n\n"}],"key":"VfXc8ZsExr"}],"key":"POf4bgcjVY"},{"type":"block","kind":"notebook-content","data":{"tags":[]},"children":[{"type":"heading","depth":2,"position":{"start":{"line":1,"column":1},"end":{"line":1,"column":1}},"children":[{"type":"text","value":"Grab Data from ","key":"hiZWLHNRUn"},{"type":"abbreviation","title":"Atmospheric Radiation Measurement","children":[{"type":"text","value":"ARM","key":"KdWjhxeRQF"}],"key":"mWbwEntG76"}],"identifier":"grab-data-from-arm","label":"Grab Data from ARM","html_id":"grab-data-from-arm","implicit":true,"key":"ivFIHMborf"},{"type":"paragraph","position":{"start":{"line":3,"column":1},"end":{"line":3,"column":1}},"children":[{"type":"text","value":"One of the better cases was from June 2, 2022, where several cold pools and single-cell storms traversed through the domain.","position":{"start":{"line":3,"column":1},"end":{"line":3,"column":1}},"key":"wY32wz1CrM"}],"key":"D1auZxHsdZ"}],"visibility":"show","key":"TV4Z3HRYgI"},{"type":"block","kind":"notebook-content","children":[{"type":"heading","depth":3,"position":{"start":{"line":1,"column":1},"end":{"line":1,"column":1}},"children":[{"type":"text","value":"The Tracking Aerosol Convection Interactions ExpeRiment (TRACER) Field Campaign","position":{"start":{"line":1,"column":1},"end":{"line":1,"column":1}},"key":"iLzPghw2Kd"}],"identifier":"the-tracking-aerosol-convection-interactions-experiment-tracer-field-campaign","label":"The Tracking Aerosol Convection Interactions ExpeRiment (TRACER) Field Campaign","html_id":"the-tracking-aerosol-convection-interactions-experiment-tracer-field-campaign","implicit":true,"key":"KPwCMHyn29"},{"type":"paragraph","position":{"start":{"line":3,"column":1},"end":{"line":3,"column":1}},"children":[{"type":"text","value":"Data is available from the Atmospheric Radiation Measurment user facility, which helped to lead the TRACER field campaign in Houston, Texas.","position":{"start":{"line":3,"column":1},"end":{"line":3,"column":1}},"key":"UMqWITvbg0"}],"key":"J8Ohw93aKH"},{"type":"paragraph","position":{"start":{"line":5,"column":1},"end":{"line":5,"column":1}},"children":[{"type":"text","value":"The data are available from the ","key":"UabFRyQiFt"},{"type":"abbreviation","title":"Atmospheric Radiation Measurement","children":[{"type":"text","value":"ARM","key":"OhY9DgE9sY"}],"key":"PJbWTjlnNg"},{"type":"text","value":" data portal (","key":"LFi94oOCF0"},{"type":"link","url":"https://adc.arm.gov/","position":{"start":{"line":5,"column":1},"end":{"line":5,"column":1}},"children":[{"type":"text","value":"https://​adc​.arm​.gov/","position":{"start":{"line":5,"column":1},"end":{"line":5,"column":1}},"key":"WtG0zk7Vfe"}],"urlSource":"https://adc.arm.gov/","key":"xl7KEjXB4N"},{"type":"text","value":").","position":{"start":{"line":5,"column":1},"end":{"line":5,"column":1}},"key":"zAQyoOuPNC"}],"key":"EAlERqCuyN"},{"type":"paragraph","position":{"start":{"line":7,"column":1},"end":{"line":7,"column":1}},"children":[{"type":"text","value":"We are interested in the C-band radar, which is utilizing a cell-tracking algorithm, with the datastream","position":{"start":{"line":7,"column":1},"end":{"line":7,"column":1}},"key":"evZgssU8Ig"}],"key":"MtX2k7b8TI"},{"type":"list","ordered":false,"spread":false,"position":{"start":{"line":8,"column":1},"end":{"line":8,"column":1}},"children":[{"type":"listItem","spread":true,"position":{"start":{"line":8,"column":1},"end":{"line":8,"column":1}},"children":[{"type":"paragraph","children":[{"type":"strong","position":{"start":{"line":8,"column":1},"end":{"line":8,"column":1}},"children":[{"type":"inlineCode","value":"houcsapr2cfrS2.a1","position":{"start":{"line":8,"column":1},"end":{"line":8,"column":1}},"key":"HBNtMQLvC4"}],"key":"VjuBNfxQ7g"}],"key":"VF64ydNNz5"}],"key":"LbSCmVuWqJ"}],"key":"X6TuqMdwuf"}],"key":"AWTJyF6Qnn"},{"type":"block","kind":"notebook-content","children":[{"type":"heading","depth":3,"position":{"start":{"line":1,"column":1},"end":{"line":1,"column":1}},"children":[{"type":"text","value":"Use the ","key":"mta12fpMCU"},{"type":"abbreviation","title":"Atmospheric Radiation Measurement","children":[{"type":"text","value":"ARM","key":"FKI3YQjUDU"}],"key":"FPZL3cZ0Y2"},{"type":"text","value":" Live API to Download the Data, using ACT","key":"yLjkqTD74a"}],"identifier":"use-the-arm-live-api-to-download-the-data-using-act","label":"Use the ARM Live API to Download the Data, using ACT","html_id":"use-the-arm-live-api-to-download-the-data-using-act","implicit":true,"key":"UiJgvosD6D"},{"type":"paragraph","position":{"start":{"line":3,"column":1},"end":{"line":3,"column":1}},"children":[{"type":"text","value":"The Atmospheric Data Community Toolkit (ACT) has a helpful module to interface with the data server:","position":{"start":{"line":3,"column":1},"end":{"line":3,"column":1}},"key":"RUhemDOh84"}],"key":"wirG3UC3tZ"},{"type":"list","ordered":false,"spread":false,"position":{"start":{"line":4,"column":1},"end":{"line":4,"column":1}},"children":[{"type":"listItem","spread":true,"position":{"start":{"line":4,"column":1},"end":{"line":4,"column":1}},"children":[{"type":"paragraph","children":[{"type":"link","url":"hhttps://arm-doe.github.io/ACT/API/generated/act.discovery.download_arm_data.html","position":{"start":{"line":4,"column":1},"end":{"line":4,"column":1}},"children":[{"type":"text","value":"Download Data API","position":{"start":{"line":4,"column":1},"end":{"line":4,"column":1}},"key":"hPf6Gw5SLN"}],"urlSource":"hhttps://arm-doe.github.io/ACT/API/generated/act.discovery.download_arm_data.html","key":"n4gEJupZAf"}],"key":"ssdwKJExBg"}],"key":"cjwUINRQAZ"}],"key":"TyHtanlfDy"}],"key":"yZm4waWQcg"},{"type":"block","kind":"notebook-code","children":[{"type":"code","lang":"python","executable":true,"value":"act.discovery.download_arm_data?","key":"isuu3lixyQ"},{"type":"output","id":"xvfGyrPuG87ftFGoYgBFs","data":[],"key":"SJl0mqJTPJ"}],"key":"FSLCz2jk2k"},{"type":"block","kind":"notebook-content","children":[{"type":"heading","depth":3,"position":{"start":{"line":1,"column":1},"end":{"line":1,"column":1}},"children":[{"type":"text","value":"Setup our Download Query","position":{"start":{"line":1,"column":1},"end":{"line":1,"column":1}},"key":"NwizKhRGCO"}],"identifier":"setup-our-download-query","label":"Setup our Download Query","html_id":"setup-our-download-query","implicit":true,"key":"MpodjiZ3vj"},{"type":"paragraph","position":{"start":{"line":2,"column":1},"end":{"line":2,"column":1}},"children":[{"type":"text","value":"Before downloading our data, we need to make sure we have an ","key":"V7GEQsT4gL"},{"type":"abbreviation","title":"Atmospheric Radiation Measurement","children":[{"type":"text","value":"ARM","key":"b9NUaPLm4d"}],"key":"F1gbVsWpXU"},{"type":"text","value":" Data Account, and ","key":"Esl4EX6G08"},{"type":"abbreviation","title":"Atmospheric Radiation Measurement","children":[{"type":"text","value":"ARM","key":"KmpujqT0kb"}],"key":"jmcTarqTAB"},{"type":"text","value":" Live token. Both of these can be found using this link:","key":"SVeEdW4IAk"}],"key":"Fduo9GAP0I"},{"type":"list","ordered":false,"spread":false,"position":{"start":{"line":3,"column":1},"end":{"line":4,"column":1}},"children":[{"type":"listItem","spread":true,"position":{"start":{"line":3,"column":1},"end":{"line":4,"column":1}},"children":[{"type":"paragraph","children":[{"type":"link","url":"https://adc.arm.gov/armlive/livedata/home","position":{"start":{"line":3,"column":1},"end":{"line":3,"column":1}},"children":[{"type":"text","value":"ARM Live Signup","position":{"start":{"line":3,"column":1},"end":{"line":3,"column":1}},"key":"tpBONmm7qx"}],"urlSource":"https://adc.arm.gov/armlive/livedata/home","key":"IYUVap85mv"}],"key":"DuEMPwEtiG"}],"key":"i5U6WNoJDV"}],"key":"wH3dQ0FEhU"},{"type":"paragraph","position":{"start":{"line":5,"column":1},"end":{"line":5,"column":1}},"children":[{"type":"text","value":"Once you sign up, you will see your token. Copy and replace that where we have ","position":{"start":{"line":5,"column":1},"end":{"line":5,"column":1}},"key":"vFD1oWfcwt"},{"type":"inlineCode","value":"arm_username","position":{"start":{"line":5,"column":1},"end":{"line":5,"column":1}},"key":"FOxZXIMFb5"},{"type":"text","value":" and ","position":{"start":{"line":5,"column":1},"end":{"line":5,"column":1}},"key":"DcFPwjf9Uy"},{"type":"inlineCode","value":"arm_password","position":{"start":{"line":5,"column":1},"end":{"line":5,"column":1}},"key":"dSi4HUykSd"},{"type":"text","value":" below.","position":{"start":{"line":5,"column":1},"end":{"line":5,"column":1}},"key":"ljZuykxpLZ"}],"key":"nCNRYoqH1k"}],"key":"YScbuBaq0k"},{"type":"block","kind":"notebook-code","children":[{"type":"code","lang":"python","executable":true,"value":"arm_username = os.getenv(\"ARM_USERNAME\")\narm_password = os.getenv(\"ARM_PASSWORD\")\n\ndatastream = \"houcsapr2cfrS2.a1\"\n\nstart_date = \"2022-06-02T11:30:00\"\nend_date = \"2022-06-02T11:40:00\"\n\nprint(len(arm_username), len(arm_password))","key":"Nh18KAuKSk"},{"type":"output","id":"bm8l-9Pz3APtX0dr1Pb8s","data":[{"output_type":"stream","name":"stdout","text":"8 16\n"}],"key":"LvALV6rWHm"}],"key":"CI1JrCHxla"},{"type":"block","kind":"notebook-code","children":[{"type":"code","lang":"python","executable":true,"value":"june2_csapr_files = act.discovery.download_arm_data(arm_username,\n                                                arm_password,\n                                                datastream,\n                                                start_date,\n                                                end_date,\n                                               )","key":"WvEoQLDEho"},{"type":"output","id":"EtWzeImXEwcMLreWoPBx7","data":[{"output_type":"stream","name":"stdout","text":"[DOWNLOADING] houcsapr2cfrS2.a1.20220602.113023.nc\n"},{"output_type":"stream","name":"stdout","text":"[DOWNLOADING] houcsapr2cfrS2.a1.20220602.113041.nc\n"},{"output_type":"stream","name":"stdout","text":"[DOWNLOADING] houcsapr2cfrS2.a1.20220602.113059.nc\n"},{"output_type":"stream","name":"stdout","text":"[DOWNLOADING] houcsapr2cfrS2.a1.20220602.113115.nc\n"},{"output_type":"stream","name":"stdout","text":"[DOWNLOADING] houcsapr2cfrS2.a1.20220602.113128.nc\n"},{"output_type":"stream","name":"stdout","text":"[DOWNLOADING] houcsapr2cfrS2.a1.20220602.113159.nc\n"},{"output_type":"stream","name":"stdout","text":"[DOWNLOADING] houcsapr2cfrS2.a1.20220602.113215.nc\n"},{"output_type":"stream","name":"stdout","text":"[DOWNLOADING] houcsapr2cfrS2.a1.20220602.113230.nc\n"},{"output_type":"stream","name":"stdout","text":"[DOWNLOADING] houcsapr2cfrS2.a1.20220602.113246.nc\n"},{"output_type":"stream","name":"stdout","text":"[DOWNLOADING] houcsapr2cfrS2.a1.20220602.113258.nc\n"},{"output_type":"stream","name":"stdout","text":"[DOWNLOADING] houcsapr2cfrS2.a1.20220602.113329.nc\n"},{"output_type":"stream","name":"stdout","text":"[DOWNLOADING] houcsapr2cfrS2.a1.20220602.113346.nc\n"},{"output_type":"stream","name":"stdout","text":"[DOWNLOADING] houcsapr2cfrS2.a1.20220602.113400.nc\n"},{"output_type":"stream","name":"stdout","text":"[DOWNLOADING] houcsapr2cfrS2.a1.20220602.113415.nc\n"},{"output_type":"stream","name":"stdout","text":"[DOWNLOADING] houcsapr2cfrS2.a1.20220602.113428.nc\n"},{"output_type":"stream","name":"stdout","text":"[DOWNLOADING] houcsapr2cfrS2.a1.20220602.113459.nc\n"},{"output_type":"stream","name":"stdout","text":"[DOWNLOADING] houcsapr2cfrS2.a1.20220602.113514.nc\n"},{"output_type":"stream","name":"stdout","text":"[DOWNLOADING] houcsapr2cfrS2.a1.20220602.113529.nc\n"},{"output_type":"stream","name":"stdout","text":"[DOWNLOADING] houcsapr2cfrS2.a1.20220602.113544.nc\n"},{"output_type":"stream","name":"stdout","text":"[DOWNLOADING] houcsapr2cfrS2.a1.20220602.113557.nc\n"},{"output_type":"stream","name":"stdout","text":"[DOWNLOADING] houcsapr2cfrS2.a1.20220602.113628.nc\n"},{"output_type":"stream","name":"stdout","text":"[DOWNLOADING] houcsapr2cfrS2.a1.20220602.113645.nc\n"},{"output_type":"stream","name":"stdout","text":"[DOWNLOADING] houcsapr2cfrS2.a1.20220602.113700.nc\n"},{"output_type":"stream","name":"stdout","text":"[DOWNLOADING] houcsapr2cfrS2.a1.20220602.113716.nc\n"},{"output_type":"stream","name":"stdout","text":"[DOWNLOADING] houcsapr2cfrS2.a1.20220602.113728.nc\n"},{"output_type":"stream","name":"stdout","text":"[DOWNLOADING] houcsapr2cfrS2.a1.20220602.113759.nc\n"},{"output_type":"stream","name":"stdout","text":"[DOWNLOADING] houcsapr2cfrS2.a1.20220602.113814.nc\n"},{"output_type":"stream","name":"stdout","text":"[DOWNLOADING] houcsapr2cfrS2.a1.20220602.113829.nc\n"},{"output_type":"stream","name":"stdout","text":"[DOWNLOADING] houcsapr2cfrS2.a1.20220602.113844.nc\n"},{"output_type":"stream","name":"stdout","text":"[DOWNLOADING] houcsapr2cfrS2.a1.20220602.113858.nc\n"},{"output_type":"stream","name":"stdout","text":"[DOWNLOADING] houcsapr2cfrS2.a1.20220602.113929.nc\n"},{"output_type":"stream","name":"stdout","text":"[DOWNLOADING] houcsapr2cfrS2.a1.20220602.113944.nc\n"},{"output_type":"stream","name":"stdout","text":"\nIf you use these data to prepare a publication, please cite:\n\nBharadwaj, N., Collis, S., Hardin, J., Isom, B., Lindenmaier, I., Matthews, A.,\nNelson, D., Feng, Y.-C., Rocque, M., Wendler, T., & Castro, V. C-Band Scanning\nARM Precipitation Radar (CSAPR2CFR), 2022-06-02 to 2022-06-02, ARM Mobile\nFacility (HOU), Houston, TX; Supplemental Facility 2 (S2). Atmospheric Radiation\nMeasurement (ARM) User Facility. https://doi.org/10.5439/1467901\n\n"}],"key":"eRDPZcmAgy"}],"key":"zS4ZSViYA1"},{"type":"block","kind":"notebook-content","children":[{"type":"heading","depth":2,"position":{"start":{"line":1,"column":1},"end":{"line":1,"column":1}},"children":[{"type":"text","value":"Read in and Plot the Data","position":{"start":{"line":1,"column":1},"end":{"line":1,"column":1}},"key":"s3YdsidUue"}],"identifier":"read-in-and-plot-the-data","label":"Read in and Plot the Data","html_id":"read-in-and-plot-the-data","implicit":true,"key":"qZ0IWaQSy2"},{"type":"paragraph","position":{"start":{"line":2,"column":1},"end":{"line":2,"column":1}},"children":[{"type":"text","value":"Before following running the next cells, make sure you have created the following directories:","position":{"start":{"line":2,"column":1},"end":{"line":2,"column":1}},"key":"I6vIlsgx4R"}],"key":"T430bdJrzb"},{"type":"list","ordered":false,"spread":false,"position":{"start":{"line":3,"column":1},"end":{"line":5,"column":1}},"children":[{"type":"listItem","spread":true,"position":{"start":{"line":3,"column":1},"end":{"line":3,"column":1}},"children":[{"type":"paragraph","children":[{"type":"inlineCode","value":"quicklooks/ppi","position":{"start":{"line":3,"column":1},"end":{"line":3,"column":1}},"key":"kaLOi0IjeQ"}],"key":"tf4e5KkmJj"}],"key":"ZMt7iwJ043"},{"type":"listItem","spread":true,"position":{"start":{"line":4,"column":1},"end":{"line":4,"column":1}},"children":[{"type":"paragraph","children":[{"type":"inlineCode","value":"quicklooks/rhi","position":{"start":{"line":4,"column":1},"end":{"line":4,"column":1}},"key":"I52HJzIth8"}],"key":"L4bT0jhh17"}],"key":"cAe9CmDM6R"},{"type":"listItem","spread":true,"position":{"start":{"line":5,"column":1},"end":{"line":5,"column":1}},"children":[{"type":"paragraph","children":[{"type":"inlineCode","value":"quicklooks/vpt","position":{"start":{"line":5,"column":1},"end":{"line":5,"column":1}},"key":"YKVHFRLo6F"}],"key":"ky4nUYcPma"}],"key":"QOsQFSNRqr"}],"key":"vON5G12LOo"}],"key":"u5fN8peHg1"},{"type":"block","kind":"notebook-code","children":[{"type":"code","lang":"python","executable":true,"value":"!mkdir quicklooks\n!mkdir quicklooks/rhi\n!mkdir quicklooks/ppi\n!mkdir quicklooks/vpt","key":"N3A9v89Uq3"},{"type":"output","id":"b9-Ii5PXwor5R381q7L7L","data":[{"output_type":"stream","name":"stdout","text":"mkdir: cannot create directory ‘quicklooks’: File exists\r\n"}],"key":"VljbS7keOg"}],"key":"oTCCVaOrJo"},{"type":"block","kind":"notebook-content","children":[{"type":"heading","depth":3,"position":{"start":{"line":1,"column":1},"end":{"line":1,"column":1}},"children":[{"type":"text","value":"Loop through and plot","position":{"start":{"line":1,"column":1},"end":{"line":1,"column":1}},"key":"p4w0U3AA0e"}],"identifier":"loop-through-and-plot","label":"Loop through and plot","html_id":"loop-through-and-plot","implicit":true,"key":"BtItVTM1fs"},{"type":"paragraph","position":{"start":{"line":2,"column":1},"end":{"line":2,"column":1}},"children":[{"type":"text","value":"We read in the data, check the scan type, and plot a basic ","position":{"start":{"line":2,"column":1},"end":{"line":2,"column":1}},"key":"WdXp50bC3C"},{"type":"inlineCode","value":"RadarDisplay","position":{"start":{"line":2,"column":1},"end":{"line":2,"column":1}},"key":"nMCevwZDRX"},{"type":"text","value":" which will automatically detect whether the plot is a vertical cross section (RHI or VPT), or a horizontal scan (PPI).","position":{"start":{"line":2,"column":1},"end":{"line":2,"column":1}},"key":"NKxnLPQVcI"}],"key":"LfE2MJ4Aw6"},{"type":"paragraph","position":{"start":{"line":4,"column":1},"end":{"line":4,"column":1}},"children":[{"type":"text","value":"This offers a solid “quick look”, or initial visualization of the data.","position":{"start":{"line":4,"column":1},"end":{"line":4,"column":1}},"key":"wWLYu2T69V"}],"key":"dgS3fq1wuU"}],"key":"WTjJB6eY0q"},{"type":"block","kind":"notebook-code","children":[{"type":"code","lang":"python","executable":true,"value":"for file in june2_csapr_files:\n    radar = pyart.io.read(file)\n    print(radar.scan_type)\n    display = pyart.graph.RadarDisplay(radar)\n    display.plot(\"reflectivity\", 0)\n    plt.savefig(f\"{radar.scan_type}_{Path(file).stem}.png\", dpi=200)\n    plt.show()\n    plt.close() ","key":"TSDMQH9LZh"},{"type":"output","id":"-po2fV_9NsZMcj9N57c4r","data":[{"output_type":"stream","name":"stdout","text":"rhi\n"},{"output_type":"display_data","metadata":{},"data":{"text/plain":{"content":"<Figure size 640x480 with 2 Axes>","content_type":"text/plain"},"image/png":{"content_type":"image/png","hash":"3b1664d817bb276576fb952c41daa147","path":"/radar-cookbook/build/3b1664d817bb276576fb952c41daa147.png"}}},{"output_type":"stream","name":"stdout","text":"rhi\n"},{"output_type":"display_data","metadata":{},"data":{"text/plain":{"content":"<Figure size 640x480 with 2 Axes>","content_type":"text/plain"},"image/png":{"content_type":"image/png","hash":"accb915fd1be7eb8e34b0b189cae9213","path":"/radar-cookbook/build/accb915fd1be7eb8e34b0b189cae9213.png"}}},{"output_type":"stream","name":"stdout","text":"rhi\n"},{"output_type":"display_data","metadata":{},"data":{"text/plain":{"content":"<Figure size 640x480 with 2 Axes>","content_type":"text/plain"},"image/png":{"content_type":"image/png","hash":"3353b428efffb3d1268cb3ca93751455","path":"/radar-cookbook/build/3353b428efffb3d1268cb3ca93751455.png"}}},{"output_type":"stream","name":"stdout","text":"rhi\n"},{"output_type":"display_data","metadata":{},"data":{"text/plain":{"content":"<Figure size 640x480 with 2 Axes>","content_type":"text/plain"},"image/png":{"content_type":"image/png","hash":"fe85db39fd7a665e52d6e0b62362496f","path":"/radar-cookbook/build/fe85db39fd7a665e52d6e0b62362496f.png"}}},{"output_type":"stream","name":"stdout","text":"sector\n"},{"output_type":"display_data","metadata":{},"data":{"text/plain":{"content":"<Figure size 640x480 with 2 Axes>","content_type":"text/plain"},"image/png":{"content_type":"image/png","hash":"88785fffb5f803e764623d494c94ed0f","path":"/radar-cookbook/build/88785fffb5f803e764623d494c94ed0f.png"}}},{"output_type":"stream","name":"stdout","text":"rhi\n"},{"output_type":"display_data","metadata":{},"data":{"text/plain":{"content":"<Figure size 640x480 with 2 Axes>","content_type":"text/plain"},"image/png":{"content_type":"image/png","hash":"109e228ef335dbf5c900ba477806ce43","path":"/radar-cookbook/build/109e228ef335dbf5c900ba477806ce43.png"}}},{"output_type":"stream","name":"stdout","text":"rhi\n"},{"output_type":"display_data","metadata":{},"data":{"text/plain":{"content":"<Figure size 640x480 with 2 Axes>","content_type":"text/plain"},"image/png":{"content_type":"image/png","hash":"3f4f3c0d52e68b9a608434f0f53691e4","path":"/radar-cookbook/build/3f4f3c0d52e68b9a608434f0f53691e4.png"}}},{"output_type":"stream","name":"stdout","text":"rhi\n"},{"output_type":"display_data","metadata":{},"data":{"text/plain":{"content":"<Figure size 640x480 with 2 Axes>","content_type":"text/plain"},"image/png":{"content_type":"image/png","hash":"29c1c6975d8ae409a0a2deca5d7fcb2f","path":"/radar-cookbook/build/29c1c6975d8ae409a0a2deca5d7fcb2f.png"}}},{"output_type":"stream","name":"stdout","text":"rhi\n"},{"output_type":"display_data","metadata":{},"data":{"text/plain":{"content":"<Figure size 640x480 with 2 Axes>","content_type":"text/plain"},"image/png":{"content_type":"image/png","hash":"3b8dbbb8d8292dc70206d48d3090e2c8","path":"/radar-cookbook/build/3b8dbbb8d8292dc70206d48d3090e2c8.png"}}},{"output_type":"stream","name":"stdout","text":"sector\n"},{"output_type":"display_data","metadata":{},"data":{"text/plain":{"content":"<Figure size 640x480 with 2 Axes>","content_type":"text/plain"},"image/png":{"content_type":"image/png","hash":"b8914bfece2732a7eb5b2e3a2b0cfd5a","path":"/radar-cookbook/build/b8914bfece2732a7eb5b2e3a2b0cfd5a.png"}}},{"output_type":"stream","name":"stdout","text":"rhi\n"},{"output_type":"display_data","metadata":{},"data":{"text/plain":{"content":"<Figure size 640x480 with 2 Axes>","content_type":"text/plain"},"image/png":{"content_type":"image/png","hash":"d5b59b29ca3a9ca8705eff1c5556513e","path":"/radar-cookbook/build/d5b59b29ca3a9ca8705eff1c5556513e.png"}}},{"output_type":"stream","name":"stdout","text":"rhi\n"},{"output_type":"display_data","metadata":{},"data":{"text/plain":{"content":"<Figure size 640x480 with 2 Axes>","content_type":"text/plain"},"image/png":{"content_type":"image/png","hash":"c3db16bec8d5485a9288510504a9f755","path":"/radar-cookbook/build/c3db16bec8d5485a9288510504a9f755.png"}}},{"output_type":"stream","name":"stdout","text":"rhi\n"},{"output_type":"display_data","metadata":{},"data":{"text/plain":{"content":"<Figure size 640x480 with 2 Axes>","content_type":"text/plain"},"image/png":{"content_type":"image/png","hash":"330857d5216ee0e6dbfc7622c8e232fb","path":"/radar-cookbook/build/330857d5216ee0e6dbfc7622c8e232fb.png"}}},{"output_type":"stream","name":"stdout","text":"rhi\n"},{"output_type":"display_data","metadata":{},"data":{"text/plain":{"content":"<Figure size 640x480 with 2 Axes>","content_type":"text/plain"},"image/png":{"content_type":"image/png","hash":"b90d633fa51a663fc714a461430379d7","path":"/radar-cookbook/build/b90d633fa51a663fc714a461430379d7.png"}}},{"output_type":"stream","name":"stdout","text":"sector\n"},{"output_type":"display_data","metadata":{},"data":{"text/plain":{"content":"<Figure size 640x480 with 2 Axes>","content_type":"text/plain"},"image/png":{"content_type":"image/png","hash":"edeed74ed2747f763a6ccc6e2adaab9a","path":"/radar-cookbook/build/edeed74ed2747f763a6ccc6e2adaab9a.png"}}},{"output_type":"stream","name":"stdout","text":"rhi\n"},{"output_type":"display_data","metadata":{},"data":{"text/plain":{"content":"<Figure size 640x480 with 2 Axes>","content_type":"text/plain"},"image/png":{"content_type":"image/png","hash":"0855283c66e220f2b99cbcf5c80f82b4","path":"/radar-cookbook/build/0855283c66e220f2b99cbcf5c80f82b4.png"}}},{"output_type":"stream","name":"stdout","text":"rhi\n"},{"output_type":"display_data","metadata":{},"data":{"text/plain":{"content":"<Figure size 640x480 with 2 Axes>","content_type":"text/plain"},"image/png":{"content_type":"image/png","hash":"da20782ff30c21d5507fcbc6ca149c19","path":"/radar-cookbook/build/da20782ff30c21d5507fcbc6ca149c19.png"}}},{"output_type":"stream","name":"stdout","text":"rhi\n"},{"output_type":"display_data","metadata":{},"data":{"text/plain":{"content":"<Figure size 640x480 with 2 Axes>","content_type":"text/plain"},"image/png":{"content_type":"image/png","hash":"efc3d37ea5e92269970e7c832c877910","path":"/radar-cookbook/build/efc3d37ea5e92269970e7c832c877910.png"}}},{"output_type":"stream","name":"stdout","text":"rhi\n"},{"output_type":"display_data","metadata":{},"data":{"text/plain":{"content":"<Figure size 640x480 with 2 Axes>","content_type":"text/plain"},"image/png":{"content_type":"image/png","hash":"92ddcdd3cdbf918257a63cfc2443aea1","path":"/radar-cookbook/build/92ddcdd3cdbf918257a63cfc2443aea1.png"}}},{"output_type":"stream","name":"stdout","text":"sector\n"},{"output_type":"display_data","metadata":{},"data":{"text/plain":{"content":"<Figure size 640x480 with 2 Axes>","content_type":"text/plain"},"image/png":{"content_type":"image/png","hash":"aff59c9ad0e4785bf602bffa34179226","path":"/radar-cookbook/build/aff59c9ad0e4785bf602bffa34179226.png"}}},{"output_type":"stream","name":"stdout","text":"rhi\n"},{"output_type":"display_data","metadata":{},"data":{"text/plain":{"content":"<Figure size 640x480 with 2 Axes>","content_type":"text/plain"},"image/png":{"content_type":"image/png","hash":"2016acd7d35a6560216091a36a5361e2","path":"/radar-cookbook/build/2016acd7d35a6560216091a36a5361e2.png"}}},{"output_type":"stream","name":"stdout","text":"rhi\n"},{"output_type":"display_data","metadata":{},"data":{"text/plain":{"content":"<Figure size 640x480 with 2 Axes>","content_type":"text/plain"},"image/png":{"content_type":"image/png","hash":"7dad053b2dbc4dc9104c059f5cb5881b","path":"/radar-cookbook/build/7dad053b2dbc4dc9104c059f5cb5881b.png"}}},{"output_type":"stream","name":"stdout","text":"rhi\n"},{"output_type":"display_data","metadata":{},"data":{"text/plain":{"content":"<Figure size 640x480 with 2 Axes>","content_type":"text/plain"},"image/png":{"content_type":"image/png","hash":"e221f8f93b47be836ccf21da354f1864","path":"/radar-cookbook/build/e221f8f93b47be836ccf21da354f1864.png"}}},{"output_type":"stream","name":"stdout","text":"rhi\n"},{"output_type":"display_data","metadata":{},"data":{"text/plain":{"content":"<Figure size 640x480 with 2 Axes>","content_type":"text/plain"},"image/png":{"content_type":"image/png","hash":"6824643f54a75cc60be30ec9b62fce52","path":"/radar-cookbook/build/6824643f54a75cc60be30ec9b62fce52.png"}}},{"output_type":"stream","name":"stdout","text":"sector\n"},{"output_type":"display_data","metadata":{},"data":{"text/plain":{"content":"<Figure size 640x480 with 2 Axes>","content_type":"text/plain"},"image/png":{"content_type":"image/png","hash":"ab01d45e2846307c5fb2a65d15594b5b","path":"/radar-cookbook/build/ab01d45e2846307c5fb2a65d15594b5b.png"}}},{"output_type":"stream","name":"stdout","text":"rhi\n"},{"output_type":"display_data","metadata":{},"data":{"text/plain":{"content":"<Figure size 640x480 with 2 Axes>","content_type":"text/plain"},"image/png":{"content_type":"image/png","hash":"c55411fd71c32c1dd437e9d2a1d933da","path":"/radar-cookbook/build/c55411fd71c32c1dd437e9d2a1d933da.png"}}},{"output_type":"stream","name":"stdout","text":"rhi\n"},{"output_type":"display_data","metadata":{},"data":{"text/plain":{"content":"<Figure size 640x480 with 2 Axes>","content_type":"text/plain"},"image/png":{"content_type":"image/png","hash":"7a9628e91abc7af34677c48d1f0910fc","path":"/radar-cookbook/build/7a9628e91abc7af34677c48d1f0910fc.png"}}},{"output_type":"stream","name":"stdout","text":"rhi\n"},{"output_type":"display_data","metadata":{},"data":{"text/plain":{"content":"<Figure size 640x480 with 2 Axes>","content_type":"text/plain"},"image/png":{"content_type":"image/png","hash":"de96d763016af51b90630023568dfd8d","path":"/radar-cookbook/build/de96d763016af51b90630023568dfd8d.png"}}},{"output_type":"stream","name":"stdout","text":"rhi\n"},{"output_type":"display_data","metadata":{},"data":{"text/plain":{"content":"<Figure size 640x480 with 2 Axes>","content_type":"text/plain"},"image/png":{"content_type":"image/png","hash":"00d9a552260c90a743fdc26699c5454f","path":"/radar-cookbook/build/00d9a552260c90a743fdc26699c5454f.png"}}},{"output_type":"stream","name":"stdout","text":"sector\n"},{"output_type":"display_data","metadata":{},"data":{"text/plain":{"content":"<Figure size 640x480 with 2 Axes>","content_type":"text/plain"},"image/png":{"content_type":"image/png","hash":"c769fa29e59acb574902ebe2821027fa","path":"/radar-cookbook/build/c769fa29e59acb574902ebe2821027fa.png"}}},{"output_type":"stream","name":"stdout","text":"rhi\n"},{"output_type":"display_data","metadata":{},"data":{"text/plain":{"content":"<Figure size 640x480 with 2 Axes>","content_type":"text/plain"},"image/png":{"content_type":"image/png","hash":"a066bfde814a0d455726d77979b1f80c","path":"/radar-cookbook/build/a066bfde814a0d455726d77979b1f80c.png"}}},{"output_type":"stream","name":"stdout","text":"rhi\n"},{"output_type":"display_data","metadata":{},"data":{"text/plain":{"content":"<Figure size 640x480 with 2 Axes>","content_type":"text/plain"},"image/png":{"content_type":"image/png","hash":"34b98baf16293220dfb041c7cbea0b64","path":"/radar-cookbook/build/34b98baf16293220dfb041c7cbea0b64.png"}}}],"key":"tfE5JUFNez"}],"key":"qhlmbh8I8z"},{"type":"block","kind":"notebook-content","data":{"tags":[]},"children":[{"type":"heading","depth":3,"position":{"start":{"line":1,"column":1},"end":{"line":1,"column":1}},"children":[{"type":"text","value":"Refine our Plot, Plot Velocity","position":{"start":{"line":1,"column":1},"end":{"line":1,"column":1}},"key":"mTUGGvsl3L"}],"identifier":"refine-our-plot-plot-velocity","label":"Refine our Plot, Plot Velocity","html_id":"refine-our-plot-plot-velocity","implicit":true,"key":"E61M53Wxyn"},{"type":"paragraph","position":{"start":{"line":2,"column":1},"end":{"line":2,"column":1}},"children":[{"type":"text","value":"Let’s focus on the vertical scans of the data, or the RHIs.","position":{"start":{"line":2,"column":1},"end":{"line":2,"column":1}},"key":"VTvtKuX4Tj"}],"key":"mj4gp5TeEX"},{"type":"paragraph","position":{"start":{"line":4,"column":1},"end":{"line":4,"column":1}},"children":[{"type":"text","value":"You’ll notice that we had some cells around 60 km from the radar, with the vertical axis less than 6 km.","position":{"start":{"line":4,"column":1},"end":{"line":4,"column":1}},"key":"Bkdv8eSCcB"}],"key":"ay4BAgbFy1"},{"type":"paragraph","position":{"start":{"line":6,"column":1},"end":{"line":6,"column":1}},"children":[{"type":"text","value":"Let’s reflect that in the plots!","position":{"start":{"line":6,"column":1},"end":{"line":6,"column":1}},"key":"yyXr7iY6ZS"}],"key":"YnethFXEDU"}],"visibility":"show","key":"rXZJArWP9k"},{"type":"block","kind":"notebook-content","children":[{"type":"heading","depth":4,"position":{"start":{"line":1,"column":1},"end":{"line":1,"column":1}},"children":[{"type":"text","value":"Customize our plot look","position":{"start":{"line":1,"column":1},"end":{"line":1,"column":1}},"key":"vDa1wMu9VA"}],"identifier":"customize-our-plot-look","label":"Customize our plot look","html_id":"customize-our-plot-look","implicit":true,"key":"SZZ9IwZsNM"},{"type":"paragraph","position":{"start":{"line":2,"column":1},"end":{"line":2,"column":1}},"children":[{"type":"text","value":"Before we plot, we can change the size of our font, and style using the following parameters:","position":{"start":{"line":2,"column":1},"end":{"line":2,"column":1}},"key":"LxFhLag0Du"}],"key":"qOrcC62LRf"}],"key":"dpwuyfDzyB"},{"type":"block","kind":"notebook-code","children":[{"type":"code","lang":"python","executable":true,"value":"font = {'family' : 'serif',\n        'weight' : 'bold',\n        'size'   : 16}\n\nmatplotlib.rc('font', **font)","key":"OkvhwImcoj"},{"type":"output","id":"tok6PPvGfJtskKB919x3I","data":[],"key":"o3gwjwbTvx"}],"key":"L6QbPwhmk6"},{"type":"block","kind":"notebook-content","children":[{"type":"heading","depth":4,"position":{"start":{"line":1,"column":1},"end":{"line":1,"column":1}},"children":[{"type":"text","value":"Apply our Plotting Loop","position":{"start":{"line":1,"column":1},"end":{"line":1,"column":1}},"key":"GlsZHjkadF"}],"identifier":"apply-our-plotting-loop","label":"Apply our Plotting Loop","html_id":"apply-our-plotting-loop","implicit":true,"key":"RcO5wWnJj8"},{"type":"paragraph","position":{"start":{"line":2,"column":1},"end":{"line":2,"column":1}},"children":[{"type":"text","value":"We:","position":{"start":{"line":2,"column":1},"end":{"line":2,"column":1}},"key":"vEdrdJIUEa"}],"key":"ItCk72ctJq"},{"type":"list","ordered":false,"spread":false,"position":{"start":{"line":3,"column":1},"end":{"line":6,"column":1}},"children":[{"type":"listItem","spread":true,"position":{"start":{"line":3,"column":1},"end":{"line":3,"column":1}},"children":[{"type":"paragraph","children":[{"type":"text","value":"Check to see if the scan is an RHI","position":{"start":{"line":3,"column":1},"end":{"line":3,"column":1}},"key":"AOsNNmvtts"}],"key":"n1ytcg1Nub"}],"key":"yYKWiWlkNB"},{"type":"listItem","spread":true,"position":{"start":{"line":4,"column":1},"end":{"line":4,"column":1}},"children":[{"type":"paragraph","children":[{"type":"text","value":"Plot the reflectivity on one subplot","position":{"start":{"line":4,"column":1},"end":{"line":4,"column":1}},"key":"tEMi1ii2F0"}],"key":"koiFOmgBAZ"}],"key":"ZJC4KG8L0h"},{"type":"listItem","spread":true,"position":{"start":{"line":5,"column":1},"end":{"line":5,"column":1}},"children":[{"type":"paragraph","children":[{"type":"text","value":"Plot velocity on the other","position":{"start":{"line":5,"column":1},"end":{"line":5,"column":1}},"key":"mSrTX7EbuR"}],"key":"Xm0Fe7EZyN"}],"key":"flUju1d3Gd"},{"type":"listItem","spread":true,"position":{"start":{"line":6,"column":1},"end":{"line":6,"column":1}},"children":[{"type":"paragraph","children":[{"type":"text","value":"Save our plots","position":{"start":{"line":6,"column":1},"end":{"line":6,"column":1}},"key":"ghS3xhGZ5v"}],"key":"JuMUmPpcjU"}],"key":"OEmgYFMNI0"}],"key":"XECd0c0SSn"}],"key":"Xyf1idpcKD"},{"type":"block","kind":"notebook-code","children":[{"type":"code","lang":"python","executable":true,"value":"for file in june2_csapr_files:\n    radar = pyart.io.read(file)\n    if radar.scan_type == 'rhi':\n        fig = plt.figure(figsize=(20,8))\n        display = pyart.graph.RadarDisplay(radar)\n        ax = plt.subplot(121)\n        display.plot(\"reflectivity\",\n                     0,\n                     ax=ax,\n                     vmin=-20,\n                     vmax=70)\n        plt.xlim(62,68)\n        plt.ylim(0, 6)\n        \n        ax2 = plt.subplot(122)\n        display.plot(\"mean_doppler_velocity\",\n                     0,\n                     ax=ax2, \n                     cmap='balance',\n                     vmin=-15,\n                     vmax=15)\n        plt.xlim(62,68)\n        plt.ylim(0, 6)\n        plt.savefig(f\"{radar.scan_type}_{Path(file).stem}.png\", dpi=200)\n        plt.show()\n        plt.close() ","key":"YabOEXcCPZ"},{"type":"output","id":"HtEsODo_e-XISbEUZPYpy","data":[{"output_type":"display_data","metadata":{},"data":{"text/plain":{"content":"<Figure size 2000x800 with 4 Axes>","content_type":"text/plain"},"image/png":{"content_type":"image/png","hash":"f928c4638ee1ebe0145b19c3207617e8","path":"/radar-cookbook/build/f928c4638ee1ebe0145b19c3207617e8.png"}}},{"output_type":"display_data","metadata":{},"data":{"text/plain":{"content":"<Figure size 2000x800 with 4 Axes>","content_type":"text/plain"},"image/png":{"content_type":"image/png","hash":"8274b6faeb51504686361b95dcf13c90","path":"/radar-cookbook/build/8274b6faeb51504686361b95dcf13c90.png"}}},{"output_type":"display_data","metadata":{},"data":{"text/plain":{"content":"<Figure size 2000x800 with 4 Axes>","content_type":"text/plain"},"image/png":{"content_type":"image/png","hash":"68943bf21a2aafd2f4a69592a220c534","path":"/radar-cookbook/build/68943bf21a2aafd2f4a69592a220c534.png"}}},{"output_type":"display_data","metadata":{},"data":{"text/plain":{"content":"<Figure size 2000x800 with 4 Axes>","content_type":"text/plain"},"image/png":{"content_type":"image/png","hash":"da27ed5e94881cd460d2d9cf04931a26","path":"/radar-cookbook/build/da27ed5e94881cd460d2d9cf04931a26.png"}}},{"output_type":"display_data","metadata":{},"data":{"text/plain":{"content":"<Figure size 2000x800 with 4 Axes>","content_type":"text/plain"},"image/png":{"content_type":"image/png","hash":"58b456089b7fb995fc6250a9b8e64113","path":"/radar-cookbook/build/58b456089b7fb995fc6250a9b8e64113.png"}}},{"output_type":"display_data","metadata":{},"data":{"text/plain":{"content":"<Figure size 2000x800 with 4 Axes>","content_type":"text/plain"},"image/png":{"content_type":"image/png","hash":"569814a985feebf07393452c890bd279","path":"/radar-cookbook/build/569814a985feebf07393452c890bd279.png"}}},{"output_type":"display_data","metadata":{},"data":{"text/plain":{"content":"<Figure size 2000x800 with 4 Axes>","content_type":"text/plain"},"image/png":{"content_type":"image/png","hash":"c89a4edcacd65e9802f3f6182a0ebcfa","path":"/radar-cookbook/build/c89a4edcacd65e9802f3f6182a0ebcfa.png"}}},{"output_type":"display_data","metadata":{},"data":{"text/plain":{"content":"<Figure size 2000x800 with 4 Axes>","content_type":"text/plain"},"image/png":{"content_type":"image/png","hash":"f3673443a3155d4a260cec65ef426bbb","path":"/radar-cookbook/build/f3673443a3155d4a260cec65ef426bbb.png"}}},{"output_type":"display_data","metadata":{},"data":{"text/plain":{"content":"<Figure size 2000x800 with 4 Axes>","content_type":"text/plain"},"image/png":{"content_type":"image/png","hash":"bab189e1519bd35475af36a92c9bb7eb","path":"/radar-cookbook/build/bab189e1519bd35475af36a92c9bb7eb.png"}}},{"output_type":"display_data","metadata":{},"data":{"text/plain":{"content":"<Figure size 2000x800 with 4 Axes>","content_type":"text/plain"},"image/png":{"content_type":"image/png","hash":"e4f30a579c82ebb1ff02bfdbac1e6663","path":"/radar-cookbook/build/e4f30a579c82ebb1ff02bfdbac1e6663.png"}}},{"output_type":"display_data","metadata":{},"data":{"text/plain":{"content":"<Figure size 2000x800 with 4 Axes>","content_type":"text/plain"},"image/png":{"content_type":"image/png","hash":"b632b177f0600299b6e35f17aabe6fd2","path":"/radar-cookbook/build/b632b177f0600299b6e35f17aabe6fd2.png"}}},{"output_type":"display_data","metadata":{},"data":{"text/plain":{"content":"<Figure size 2000x800 with 4 Axes>","content_type":"text/plain"},"image/png":{"content_type":"image/png","hash":"0d523f8ef57b95758c8e789ade56f3d9","path":"/radar-cookbook/build/0d523f8ef57b95758c8e789ade56f3d9.png"}}},{"output_type":"display_data","metadata":{},"data":{"text/plain":{"content":"<Figure size 2000x800 with 4 Axes>","content_type":"text/plain"},"image/png":{"content_type":"image/png","hash":"608d4ae86f3d853587c7f8f68dd249b0","path":"/radar-cookbook/build/608d4ae86f3d853587c7f8f68dd249b0.png"}}},{"output_type":"display_data","metadata":{},"data":{"text/plain":{"content":"<Figure size 2000x800 with 4 Axes>","content_type":"text/plain"},"image/png":{"content_type":"image/png","hash":"64d1bb287c38a19411cb0655308f26bb","path":"/radar-cookbook/build/64d1bb287c38a19411cb0655308f26bb.png"}}},{"output_type":"display_data","metadata":{},"data":{"text/plain":{"content":"<Figure size 2000x800 with 4 Axes>","content_type":"text/plain"},"image/png":{"content_type":"image/png","hash":"1e732a25011c457e9ac2b3c49f6c8f8d","path":"/radar-cookbook/build/1e732a25011c457e9ac2b3c49f6c8f8d.png"}}},{"output_type":"display_data","metadata":{},"data":{"text/plain":{"content":"<Figure size 2000x800 with 4 Axes>","content_type":"text/plain"},"image/png":{"content_type":"image/png","hash":"b2ab0714840c67a3a1154bcea6103f2d","path":"/radar-cookbook/build/b2ab0714840c67a3a1154bcea6103f2d.png"}}},{"output_type":"display_data","metadata":{},"data":{"text/plain":{"content":"<Figure size 2000x800 with 4 Axes>","content_type":"text/plain"},"image/png":{"content_type":"image/png","hash":"b3d2716f735c53f46d1115f9732c0072","path":"/radar-cookbook/build/b3d2716f735c53f46d1115f9732c0072.png"}}},{"output_type":"display_data","metadata":{},"data":{"text/plain":{"content":"<Figure size 2000x800 with 4 Axes>","content_type":"text/plain"},"image/png":{"content_type":"image/png","hash":"089d175c40597e0fdfc6960622631df0","path":"/radar-cookbook/build/089d175c40597e0fdfc6960622631df0.png"}}},{"output_type":"display_data","metadata":{},"data":{"text/plain":{"content":"<Figure size 2000x800 with 4 Axes>","content_type":"text/plain"},"image/png":{"content_type":"image/png","hash":"e4909fa572b2d2f1896ca86454f37a70","path":"/radar-cookbook/build/e4909fa572b2d2f1896ca86454f37a70.png"}}},{"output_type":"display_data","metadata":{},"data":{"text/plain":{"content":"<Figure size 2000x800 with 4 Axes>","content_type":"text/plain"},"image/png":{"content_type":"image/png","hash":"e8f919f92302db0ebfcb7dec54128c0d","path":"/radar-cookbook/build/e8f919f92302db0ebfcb7dec54128c0d.png"}}},{"output_type":"display_data","metadata":{},"data":{"text/plain":{"content":"<Figure size 2000x800 with 4 Axes>","content_type":"text/plain"},"image/png":{"content_type":"image/png","hash":"07ff6b3cd0416007af9e53ed0bed9951","path":"/radar-cookbook/build/07ff6b3cd0416007af9e53ed0bed9951.png"}}},{"output_type":"display_data","metadata":{},"data":{"text/plain":{"content":"<Figure size 2000x800 with 4 Axes>","content_type":"text/plain"},"image/png":{"content_type":"image/png","hash":"ff4c1f855a308a4c9dce1115dc49137d","path":"/radar-cookbook/build/ff4c1f855a308a4c9dce1115dc49137d.png"}}},{"output_type":"display_data","metadata":{},"data":{"text/plain":{"content":"<Figure size 2000x800 with 4 Axes>","content_type":"text/plain"},"image/png":{"content_type":"image/png","hash":"2245d22fc206cbbb7634d4bc9a784f25","path":"/radar-cookbook/build/2245d22fc206cbbb7634d4bc9a784f25.png"}}},{"output_type":"display_data","metadata":{},"data":{"text/plain":{"content":"<Figure size 2000x800 with 4 Axes>","content_type":"text/plain"},"image/png":{"content_type":"image/png","hash":"be5e1676f5dd94265b9aa455fa3bfabc","path":"/radar-cookbook/build/be5e1676f5dd94265b9aa455fa3bfabc.png"}}},{"output_type":"display_data","metadata":{},"data":{"text/plain":{"content":"<Figure size 2000x800 with 4 Axes>","content_type":"text/plain"},"image/png":{"content_type":"image/png","hash":"36b745517dbc4d2a9b0f2dcec9f46aa0","path":"/radar-cookbook/build/36b745517dbc4d2a9b0f2dcec9f46aa0.png"}}},{"output_type":"display_data","metadata":{},"data":{"text/plain":{"content":"<Figure size 2000x800 with 4 Axes>","content_type":"text/plain"},"image/png":{"content_type":"image/png","hash":"00f3855bf0abc10c469303b5af43a9c0","path":"/radar-cookbook/build/00f3855bf0abc10c469303b5af43a9c0.png"}}}],"key":"VIlwMbQ807"}],"key":"MjjTKw4Qtn"},{"type":"block","kind":"notebook-content","children":[{"type":"heading","depth":3,"position":{"start":{"line":1,"column":1},"end":{"line":1,"column":1}},"children":[{"type":"text","value":"Create a GIF of the RHI images","position":{"start":{"line":1,"column":1},"end":{"line":1,"column":1}},"key":"AeIZUzRdEO"}],"identifier":"create-a-gif-of-the-rhi-images","label":"Create a GIF of the RHI images","html_id":"create-a-gif-of-the-rhi-images","implicit":true,"key":"SOfiTS8I5n"}],"key":"wjWhYerR6i"},{"type":"block","kind":"notebook-code","children":[{"type":"code","lang":"python","executable":true,"value":"rhi_images = sorted(glob.glob(f\"{radar.scan_type}*\"))","key":"h3RyWRBjH0"},{"type":"output","id":"bpl3VBszHQ_8_rIdoelVK","data":[],"key":"UnyvANU8NN"}],"key":"xoY2LrxxMs"},{"type":"block","kind":"notebook-code","children":[{"type":"code","lang":"python","executable":true,"value":"with imageio.get_writer('storm-animation.gif', mode='I') as writer:\n    for filename in rhi_images:\n        image = imageio.imread(filename)\n        writer.append_data(image)","key":"kWc1bFG9O9"},{"type":"output","id":"1o68lqjhbGF8W3N_O1bp8","data":[],"key":"UGdLTSdCrR"}],"key":"pyF0n5Uh1v"},{"type":"block","kind":"notebook-content","children":[{"type":"image","url":"/radar-cookbook/build/storm-animation-0e4e7542dff51cc4298935034d719dba.gif","width":750,"key":"KM8Jnwd0e7","urlSource":"storm-animation.gif"}],"key":"S2NVxdrZb4"},{"type":"block","kind":"notebook-content","children":[{"type":"thematicBreak","position":{"start":{"line":1,"column":1},"end":{"line":1,"column":1}},"key":"v0pdFFXgyj"},{"type":"heading","depth":2,"position":{"start":{"line":2,"column":1},"end":{"line":2,"column":1}},"children":[{"type":"text","value":"Summary","position":{"start":{"line":2,"column":1},"end":{"line":2,"column":1}},"key":"BCEBtnJyV6"}],"identifier":"summary","label":"Summary","html_id":"summary","implicit":true,"key":"y0CAv3xjMj"},{"type":"paragraph","position":{"start":{"line":3,"column":1},"end":{"line":3,"column":1}},"children":[{"type":"text","value":"Within this example, we walked through how to access ","key":"nr8DwbUy3a"},{"type":"abbreviation","title":"Atmospheric Radiation Measurement","children":[{"type":"text","value":"ARM","key":"k0enq56Sj2"}],"key":"sQsWtvSKxz"},{"type":"text","value":" data from a field campaign in Texas, plot a quick look of the data, and refine our plots to investigate a storm!","key":"wpo7qh2DV7"}],"key":"MToWMHU5CZ"},{"type":"heading","depth":3,"position":{"start":{"line":5,"column":1},"end":{"line":5,"column":1}},"children":[{"type":"text","value":"What’s Next?","position":{"start":{"line":5,"column":1},"end":{"line":5,"column":1}},"key":"G47yY3oggq"}],"identifier":"whats-next","label":"What’s Next?","html_id":"whats-next","implicit":true,"key":"gAU10zcw1X"},{"type":"paragraph","position":{"start":{"line":6,"column":1},"end":{"line":6,"column":1}},"children":[{"type":"text","value":"We will showcase other data workflow examples, including field campaigns in other regions and data access methods from other data centers.","position":{"start":{"line":6,"column":1},"end":{"line":6,"column":1}},"key":"V7NkQATFXj"}],"key":"ah1B1t6kGE"}],"key":"PrOyLjndVM"},{"type":"block","kind":"notebook-content","children":[{"type":"heading","depth":2,"position":{"start":{"line":1,"column":1},"end":{"line":1,"column":1}},"children":[{"type":"text","value":"Resources and References","position":{"start":{"line":1,"column":1},"end":{"line":1,"column":1}},"key":"mDh8cUjnOF"}],"identifier":"resources-and-references","label":"Resources and References","html_id":"resources-and-references","implicit":true,"key":"MsubuefW4O"},{"type":"list","ordered":false,"spread":false,"position":{"start":{"line":2,"column":1},"end":{"line":9,"column":1}},"children":[{"type":"listItem","spread":true,"position":{"start":{"line":2,"column":1},"end":{"line":2,"column":1}},"children":[{"type":"paragraph","children":[{"type":"link","url":"https://adc.arm.gov/discovery","position":{"start":{"line":2,"column":1},"end":{"line":2,"column":1}},"children":[{"type":"text","value":"ARM Data Discovery","position":{"start":{"line":2,"column":1},"end":{"line":2,"column":1}},"key":"SVipUgSFAn"}],"urlSource":"https://adc.arm.gov/discovery","key":"sqZCQMCuvr"}],"key":"an2n7Lv2Xe"}],"key":"AwcPWPnpgZ"},{"type":"listItem","spread":true,"position":{"start":{"line":3,"column":1},"end":{"line":3,"column":1}},"children":[{"type":"paragraph","children":[{"type":"link","url":"https://www.arm.gov/research/campaigns/amf2021tracer","position":{"start":{"line":3,"column":1},"end":{"line":3,"column":1}},"children":[{"type":"text","value":"TRACER Field Campaign","position":{"start":{"line":3,"column":1},"end":{"line":3,"column":1}},"key":"Hd3GA0egs3"}],"urlSource":"https://www.arm.gov/research/campaigns/amf2021tracer","key":"CPmtvqVVqJ"}],"key":"MCsJx22gn5"}],"key":"Q6VmweiSs3"},{"type":"listItem","spread":true,"position":{"start":{"line":4,"column":1},"end":{"line":5,"column":1}},"children":[{"type":"paragraph","children":[{"type":"text","value":"CSAPR Radar Data:","position":{"start":{"line":4,"column":1},"end":{"line":4,"column":1}},"key":"ExR5CBIkC1"}],"key":"XW4RX37fHp"},{"type":"list","ordered":false,"spread":false,"position":{"start":{"line":5,"column":1},"end":{"line":5,"column":1}},"children":[{"type":"listItem","spread":true,"position":{"start":{"line":5,"column":1},"end":{"line":5,"column":1}},"children":[{"type":"paragraph","children":[{"type":"text","value":"Bharadwaj, N., Collis, S., Hardin, J., Isom, B., Lindenmaier, I., Matthews, A., & Nelson, D. C-Band Scanning ","key":"bax5jPV1TV"},{"type":"abbreviation","title":"Atmospheric Radiation Measurement","children":[{"type":"text","value":"ARM","key":"x5sKZKwDlj"}],"key":"TF0lOd1ToX"},{"type":"text","value":" Precipitation Radar (CSAPR2CFR). Atmospheric Radiation Measurement (","key":"GK0P01drcr"},{"type":"abbreviation","title":"Atmospheric Radiation Measurement","children":[{"type":"text","value":"ARM","key":"neJOLXUfl7"}],"key":"YPY86KYIFG"},{"type":"text","value":") User Facility. ","key":"CWJWabgqhK"},{"type":"cite","url":"https://doi.org/10.5439/1467901","position":{"start":{"line":5,"column":1},"end":{"line":5,"column":1}},"children":[{"type":"text","value":"Bharadwaj ","key":"tF5O3hb2Q4"},{"type":"emphasis","children":[{"type":"text","value":"et al.","key":"Ku7KnTyaeF"}],"key":"n1zLbmdevp"},{"type":"text","value":" (2021)","key":"QUeE24HeYq"}],"kind":"narrative","label":"https://doi.org/10.5439/1467901","identifier":"https://doi.org/10.5439/1467901","enumerator":"1","key":"wFWHQ1QDgD"}],"key":"mnytY4s62U"}],"key":"pjPorwsyEN"}],"key":"DzwvVsUr3b"}],"key":"bAuSL7ZK8W"},{"type":"listItem","spread":true,"position":{"start":{"line":6,"column":1},"end":{"line":7,"column":1}},"children":[{"type":"paragraph","children":[{"type":"text","value":"Py-ART:","position":{"start":{"line":6,"column":1},"end":{"line":6,"column":1}},"key":"nl6qeCuW0X"}],"key":"qdlvskzQ3J"},{"type":"list","ordered":false,"spread":false,"position":{"start":{"line":7,"column":1},"end":{"line":7,"column":1}},"children":[{"type":"listItem","spread":true,"position":{"start":{"line":7,"column":1},"end":{"line":7,"column":1}},"children":[{"type":"paragraph","children":[{"type":"text","value":"Helmus, J.J. & Collis, S.M., (2016). The Python ","key":"RL2Inl0SDe"},{"type":"abbreviation","title":"Atmospheric Radiation Measurement","children":[{"type":"text","value":"ARM","key":"fvFlKIeSg6"}],"key":"k6kqY4Rvff"},{"type":"text","value":" Radar Toolkit (Py-ART), a Library for Working with Weather Radar Data in the Python Programming Language. Journal of Open Research Software. 4(1), p.e25. DOI: ","key":"DCr8PNnZTE"},{"type":"cite","url":"http://doi.org/10.5334/jors.119","position":{"start":{"line":7,"column":1},"end":{"line":7,"column":1}},"children":[{"type":"text","value":"Helmus & Collis (2016)","key":"LR092dR6uT"}],"kind":"narrative","label":"Helmus_2016","identifier":"http://doi.org/10.5334/jors.119","enumerator":"2","key":"MCy7Yub2n6"}],"key":"KDbscrG1NE"}],"key":"nAvbKps1jt"}],"key":"bBVrBzWQSs"}],"key":"hItNET8Gg6"},{"type":"listItem","spread":true,"position":{"start":{"line":8,"column":1},"end":{"line":9,"column":1}},"children":[{"type":"paragraph","children":[{"type":"text","value":"ACT:","position":{"start":{"line":8,"column":1},"end":{"line":8,"column":1}},"key":"NQVQ6x2F6W"}],"key":"ZQUhTGOxUi"},{"type":"list","ordered":false,"spread":false,"position":{"start":{"line":9,"column":1},"end":{"line":9,"column":1}},"children":[{"type":"listItem","spread":true,"position":{"start":{"line":9,"column":1},"end":{"line":9,"column":1}},"children":[{"type":"paragraph","children":[{"type":"text","value":"Adam Theisen, Ken Kehoe, Zach Sherman, Bobby Jackson, Alyssa Sockol, Corey Godine, Max Grover, Jason Hemedinger, Jenni Kyrouac, Maxwell Levin, Michael Giansiracusa (2022). The Atmospheric Data Community Toolkit (ACT). Zenodo. DOI: ","position":{"start":{"line":9,"column":1},"end":{"line":9,"column":1}},"key":"JlvAZ1ydSr"},{"type":"cite","url":"https://doi.org/10.5281/zenodo.6712343","position":{"start":{"line":9,"column":1},"end":{"line":9,"column":1}},"children":[{"type":"text","value":"Theisen ","key":"bRIPDXEa0H"},{"type":"emphasis","children":[{"type":"text","value":"et al.","key":"wqPU9nul25"}],"key":"q9cJWENXbl"},{"type":"text","value":" (2022)","key":"moFaVh2GUE"}],"kind":"narrative","label":"https://doi.org/10.5281/zenodo.6712343","identifier":"https://doi.org/10.5281/zenodo.6712343","enumerator":"3","key":"NbR3sojDJM"}],"key":"CMjyqzKgJN"}],"key":"WJFWu9YHUZ"}],"key":"qHkldZThr7"}],"key":"b4zhppENwV"}],"key":"RY7EslGK5W"}],"key":"KHfw2kT6ut"}],"key":"jI60J0Wuw9"},"references":{"cite":{"order":["https://doi.org/10.5439/1467901","Helmus_2016","https://doi.org/10.5281/zenodo.6712343"],"data":{"https://doi.org/10.5439/1467901":{"label":"https://doi.org/10.5439/1467901","enumerator":"1","doi":"10.5439/1467901","html":"Bharadwaj, N., Collis, S., Hardin, J., Isom, B., Lindenmaier, I., Matthews, A., Nelson, D., Feng, Y.-C., Rocque, M., Wendler, T., & Castro, V. (2021). <i>C-Band Scanning ARM Precipitation Radar, 2nd Generation</i>. Atmospheric Radiation Measurement (ARM) Archive, Oak Ridge National Laboratory (ORNL), Oak Ridge, TN (US); ARM Data Center, Oak Ridge National Laboratory (ORNL), Oak Ridge, TN (United States). <a target=\"_blank\" rel=\"noreferrer\" href=\"https://doi.org/10.5439/1467901\">10.5439/1467901</a>","url":"https://doi.org/10.5439/1467901"},"Helmus_2016":{"label":"Helmus_2016","enumerator":"2","doi":"10.5334/jors.119","html":"Helmus, J. J., & Collis, S. M. (2016). The Python ARM Radar Toolkit (Py-ART), a Library for Working with Weather Radar Data in the Python Programming Language. <i>Journal of Open Research Software</i>, <i>4</i>(1), 25. <a target=\"_blank\" rel=\"noreferrer\" href=\"https://doi.org/10.5334/jors.119\">10.5334/jors.119</a>","url":"https://doi.org/10.5334/jors.119"},"https://doi.org/10.5281/zenodo.6712343":{"label":"https://doi.org/10.5281/zenodo.6712343","enumerator":"3","doi":"10.5281/ZENODO.6712343","html":"Theisen, A., Kehoe, K., Sherman, Z., Jackson, B., Sockol, A., Godine, C., Grover, M., Hemedinger, J., Kyrouac, J., Levin, M., & Giansiracusa, M. (2022). <i>ARM-DOE/ACT: ACT Release v1.1.9</i>. Zenodo. <a target=\"_blank\" rel=\"noreferrer\" href=\"https://doi.org/10.5281/ZENODO.6712343\">10.5281/ZENODO.6712343</a>","url":"https://doi.org/10.5281/ZENODO.6712343"}}}},"footer":{"navigation":{"prev":{"title":"Looking at NEXRAD Data from Moore, Oklahoma","url":"/notebooks/example-workflows/moore-oklahoma-tornado","group":"Example Workflows"},"next":{"title":"Specific Differential Phase (K_{DP}) retrieval methods comparison","url":"/notebooks/example-workflows/kdp-comparison","group":"Example Workflows"}}},"domain":"http://localhost:3000"}